mazetool/__init__.py
mazetool/mazetool.py
mazetool-1.0.0.dist-info/DESCRIPTION.rst
mazetool-1.0.0.dist-info/METADATA
mazetool-1.0.0.dist-info/RECORD
mazetool-1.0.0.dist-info/WHEEL
mazetool-1.0.0.dist-info/entry_points.txt
mazetool-1.0.0.dist-info/metadata.json
mazetool-1.0.0.dist-info/top_level.txt
