Metadata-Version: 2.0
Name: mazetool
Version: 1.0.0
Summary: A simple maze tool for managing 2D mazes using a cli.
Home-page: https://github.com/ParthKolekar/mazetool
Author: Parth Kolekar
Author-email: parth.kolekar@students.iiit.ac.in
License: ISCL
Keywords: mazetool
Platform: UNKNOWN
Classifier: Development Status :: 2 - Pre-Alpha
Classifier: Intended Audience :: Developers
Classifier: License :: OSI Approved :: ISC License (ISCL)
Classifier: Natural Language :: English
Classifier: Programming Language :: Python :: 2
Classifier: Programming Language :: Python :: 2.6
Classifier: Programming Language :: Python :: 2.7
Classifier: Programming Language :: Python :: 3
Classifier: Programming Language :: Python :: 3.3
Classifier: Programming Language :: Python :: 3.4
Classifier: Programming Language :: Python :: 3.5
